atooms/__init__.py
atooms/parallel_tempering/__init__.py
atooms/parallel_tempering/_version.py
atooms/parallel_tempering/core.py
atooms/parallel_tempering/exchange.py
atooms/parallel_tempering/helpers.py
atooms/parallel_tempering/observers.py
atooms_pt-1.1.1.data/scripts/pt.py
atooms_pt-1.1.1.dist-info/DESCRIPTION.rst
atooms_pt-1.1.1.dist-info/METADATA
atooms_pt-1.1.1.dist-info/RECORD
atooms_pt-1.1.1.dist-info/WHEEL
atooms_pt-1.1.1.dist-info/metadata.json
atooms_pt-1.1.1.dist-info/top_level.txt
