Metadata-Version: 2.0
Name: atooms-pt
Version: 1.1.1
Summary: Multi-CPU / multi-GPU parallel tempering
Home-page: https://gitlab.info-ufr.univ-montp2.fr/daniele.coslovich/atooms/parallel_tempering
Author: Daniele Coslovich
Author-email: daniele.coslovich@umontpellier.fr
License: GPLv3
Platform: UNKNOWN
Classifier: License :: OSI Approved :: GNU General Public License v3 (GPLv3)
Classifier: Development Status :: 5 - Production/Stable
Classifier: Programming Language :: Python
Classifier: Programming Language :: Python :: 2
Classifier: Programming Language :: Python :: 2.7
Classifier: Intended Audience :: Science/Research
Classifier: Topic :: Scientific/Engineering :: Physics
Requires-Dist: atooms (>=1)
